[
    {
        "key": "dbln",
        "value": "%7B%22100066374970288%22%3A%22HEcRbtsG%22%2C%2261570101112675%22%3A%224BwkQD9u%22%2C%2261569468204521%22%3A%22yWMWwzFj%22%2C%22100095088137702%22%3A%22ReLztf2L%22%2C%2261569975990306%22%3A%22XHtKMeBA%22%2C%2261566994346640%22%3A%22QtCYXjZc%22%2C%22100085711685382%22%3A%22BBKm2FSq%22%2C%2261565605045900%22%3A%22qqpUt5Gb%22%7D",
        "domain": "facebook.com",
        "path": "/login/device-based/",
        "hostOnly": false,
        "creation": "2025-01-31T10:29:21.871Z",
        "lastAccessed": "2025-01-31T10:29:21.871Z"
    },
    {
        "key": "datr",
        "value": "FZRIZwOVbg6gfV0Db-gDwE4d",
        "domain": "facebook.com",
        "path": "/",
        "hostOnly": false,
        "creation": "2025-01-31T10:29:21.871Z",
        "lastAccessed": "2025-01-31T10:29:21.871Z"
    },
    {
        "key": "sb",
        "value": "FZRIZwUdRxz7LeJC6ggKkRyw",
        "domain": "facebook.com",
        "path": "/",
        "hostOnly": false,
        "creation": "2025-01-31T10:29:21.871Z",
        "lastAccessed": "2025-01-31T10:29:21.871Z"
    },
    {
        "key": "ps_l",
        "value": "1",
        "domain": "facebook.com",
        "path": "/",
        "hostOnly": false,
        "creation": "2025-01-31T10:29:21.871Z",
        "lastAccessed": "2025-01-31T10:29:21.871Z"
    },
    {
        "key": "ps_n",
        "value": "1",
        "domain": "facebook.com",
        "path": "/",
        "hostOnly": false,
        "creation": "2025-01-31T10:29:21.871Z",
        "lastAccessed": "2025-01-31T10:29:21.871Z"
    },
    {
        "key": "locale",
        "value": "en_US",
        "domain": "facebook.com",
        "path": "/",
        "hostOnly": false,
        "creation": "2025-01-31T10:29:21.871Z",
        "lastAccessed": "2025-01-31T10:29:21.871Z"
    },
    {
        "key": "m_pixel_ratio",
        "value": "1.8000000715255737",
        "domain": "facebook.com",
        "path": "/",
        "hostOnly": false,
        "creation": "2025-01-31T10:29:21.871Z",
        "lastAccessed": "2025-01-31T10:29:21.871Z"
    },
    {
        "key": "wd",
        "value": "400x364",
        "domain": "facebook.com",
        "path": "/",
        "hostOnly": false,
        "creation": "2025-01-31T10:29:21.871Z",
        "lastAccessed": "2025-01-31T10:29:21.871Z"
    },
    {
        "key": "c_user",
        "value": "61565488987561",
        "domain": "facebook.com",
        "path": "/",
        "hostOnly": false,
        "creation": "2025-01-31T10:29:21.871Z",
        "lastAccessed": "2025-01-31T10:29:21.871Z"
    },
    {
        "key": "xs",
        "value": "6%3A3h6SuLaVb8gxvw%3A2%3A1738319354%3A-1%3A7860",
        "domain": "facebook.com",
        "path": "/",
        "hostOnly": false,
        "creation": "2025-01-31T10:29:21.871Z",
        "lastAccessed": "2025-01-31T10:29:21.871Z"
    },
    {
        "key": "fr",
        "value": "0VvZXx0aQMTHphTsO.AWWijy-9ceHDmz5Ut1ASnWV9FBWSCOShW6wJNA.BnSJQV..AAA.0.0.BnnKX7.AWXG8gjdWYI",
        "domain": "facebook.com",
        "path": "/",
        "hostOnly": false,
        "creation": "2025-01-31T10:29:21.871Z",
        "lastAccessed": "2025-01-31T10:29:21.871Z"
    },
    {
        "key": "fbl_st",
        "value": "101530014%3BT%3A28971989",
        "domain": "facebook.com",
        "path": "/",
        "hostOnly": false,
        "creation": "2025-01-31T10:29:21.871Z",
        "lastAccessed": "2025-01-31T10:29:21.871Z"
    },
    {
        "key": "wl_cbv",
        "value": "v2%3Bclient_version%3A2729%3Btimestamp%3A1738319355",
        "domain": "facebook.com",
        "path": "/",
        "hostOnly": false,
        "creation": "2025-01-31T10:29:21.871Z",
        "lastAccessed": "2025-01-31T10:29:21.871Z"
    },
    {
        "key": "vpd",
        "value": "v1%3B364x400x1.8000000715255737",
        "domain": "facebook.com",
        "path": "/",
        "hostOnly": false,
        "creation": "2025-01-31T10:29:21.871Z",
        "lastAccessed": "2025-01-31T10:29:21.871Z"
    }
]
