[
    {
        "key": "dbln",
        "value": "%7B%2261565488987561%22%3A%22tuMM2Hcr%22%2C%2261565531410030%22%3A%22mevVBklq%22%2C%2261567145660497%22%3A%22CxC6NdFH%22%2C%22100086673919308%22%3A%22K9vwPojT%22%7D",
        "domain": "facebook.com",
        "path": "/login/device-based/",
        "hostOnly": false,
        "creation": "2024-11-06T02:03:44.065Z",
        "lastAccessed": "2024-11-06T02:03:44.066Z"
    },
    {
        "key": "datr",
        "value": "Q4T2ZlWRleYNMmLNY33KuFTg",
        "domain": "facebook.com",
        "path": "/",
        "hostOnly": false,
        "creation": "2024-11-06T02:03:44.066Z",
        "lastAccessed": "2024-11-06T02:03:44.066Z"
    },
    {
        "key": "sb",
        "value": "Q4T2ZrTR6kB-mqNHqhPXwi0r",
        "domain": "facebook.com",
        "path": "/",
        "hostOnly": false,
        "creation": "2024-11-06T02:03:44.066Z",
        "lastAccessed": "2024-11-06T02:03:44.066Z"
    },
    {
        "key": "ps_l",
        "value": "1",
        "domain": "facebook.com",
        "path": "/",
        "hostOnly": false,
        "creation": "2024-11-06T02:03:44.066Z",
        "lastAccessed": "2024-11-06T02:03:44.066Z"
    },
    {
        "key": "ps_n",
        "value": "1",
        "domain": "facebook.com",
        "path": "/",
        "hostOnly": false,
        "creation": "2024-11-06T02:03:44.066Z",
        "lastAccessed": "2024-11-06T02:03:44.066Z"
    },
    {
        "key": "locale",
        "value": "en_US",
        "domain": "facebook.com",
        "path": "/",
        "hostOnly": false,
        "creation": "2024-11-06T02:03:44.066Z",
        "lastAccessed": "2024-11-06T02:03:44.066Z"
    },
    {
        "key": "dpr",
        "value": "1.8000000715255737",
        "domain": "facebook.com",
        "path": "/",
        "hostOnly": false,
        "creation": "2024-11-06T02:03:44.066Z",
        "lastAccessed": "2024-11-06T02:03:44.066Z"
    },
    {
        "key": "vpd",
        "value": "v1%3B745x400x1.8000000715255737",
        "domain": "facebook.com",
        "path": "/",
        "hostOnly": false,
        "creation": "2024-11-06T02:03:44.066Z",
        "lastAccessed": "2024-11-06T02:03:44.066Z"
    },
    {
        "key": "wd",
        "value": "400x745",
        "domain": "facebook.com",
        "path": "/",
        "hostOnly": false,
        "creation": "2024-11-06T02:03:44.067Z",
        "lastAccessed": "2024-11-06T02:03:44.067Z"
    },
    {
        "key": "c_user",
        "value": "61565488987561",
        "domain": "facebook.com",
        "path": "/",
        "hostOnly": false,
        "creation": "2024-11-06T02:03:44.067Z",
        "lastAccessed": "2024-11-06T02:03:44.067Z"
    },
    {
        "key": "fr",
        "value": "1zDm1fXu79SnoPCtr.AWUZkgTEiJJBnYNphOuUBF8os9E.BnABXR..AAA.0.0.BnKlkB.AWXSQQSTNpU",
        "domain": "facebook.com",
        "path": "/",
        "hostOnly": false,
        "creation": "2024-11-06T02:03:44.067Z",
        "lastAccessed": "2024-11-06T02:03:44.067Z"
    },
    {
        "key": "xs",
        "value": "34%3AogOQ7cT3Ck0zHg%3A2%3A1730828545%3A-1%3A12260",
        "domain": "facebook.com",
        "path": "/",
        "hostOnly": false,
        "creation": "2024-11-06T02:03:44.067Z",
        "lastAccessed": "2024-11-06T02:03:44.067Z"
    },
    {
        "key": "fbl_st",
        "value": "101433652%3BT%3A28847643",
        "domain": "facebook.com",
        "path": "/",
        "hostOnly": false,
        "creation": "2024-11-06T02:03:44.067Z",
        "lastAccessed": "2024-11-06T02:03:44.067Z"
    },
    {
        "key": "wl_cbv",
        "value": "v2%3Bclient_version%3A2664%3Btimestamp%3A1730858618",
        "domain": "facebook.com",
        "path": "/",
        "hostOnly": false,
        "creation": "2024-11-06T02:03:44.067Z",
        "lastAccessed": "2024-11-06T02:03:44.067Z"
    }
]
